README.md
setup.cfg
setup.py
genderdecoder3/__init__.py
genderdecoder3/assess.py
genderdecoder3/wordlists.py
genderdecoder3.egg-info/PKG-INFO
genderdecoder3.egg-info/SOURCES.txt
genderdecoder3.egg-info/dependency_links.txt
genderdecoder3.egg-info/not-zip-safe
genderdecoder3.egg-info/top_level.txt