Metadata-Version: 1.0
Name: genderdecoder3
Version: 0.5
Summary: Check for gender-coded words in job adverts. A package of the service provided at http://gender-decoder.katmatfield.com
Home-page: http://github.com/robbell/genderdecoder
Author: Rob Bell
Author-email: UNKNOWN
License: MIT
Platform: UNKNOWN
